repickle/__init__.py
repickle/cloudpickle.py
repickle/cloudpickle_fast.py
repickle/compat.py
repickle/repickle.py
tests/__init__.py
repickle-0.1.0.dist-info/LICENSE
repickle-0.1.0.dist-info/METADATA
repickle-0.1.0.dist-info/WHEEL
repickle-0.1.0.dist-info/top_level.txt
repickle-0.1.0.dist-info/RECORD
