Metadata-Version: 2.1
Name: repickle
Version: 0.1.0
Summary: Extended pickling support for Python object
Home-page: https://github.com/ecanuto/repickle
Author: Everaldo Canuto
Author-email: everaldo.canuto@gmail.com
License: BSD 3-Clause License
Project-URL: Bug Tracker, https://github.com/ecanuto/repickle/issues
Platform: UNKNOWN
Classifier: Development Status :: 4 - Beta
Classifier: Intended Audience :: Developers
Classifier: License :: OSI Approved :: BSD License
Classifier: Operating System :: OS Independent
Classifier: Programming Language :: Python :: 3
Classifier: Topic :: Software Development :: Libraries :: Python Modules
Classifier: Topic :: Scientific/Engineering
Classifier: Topic :: System :: Distributed Computing
Requires-Python: >=3.6
License-File: LICENSE
